streamlit_image_carousel/__init__.py
streamlit_image_carousel/frontend/build/index.html
streamlit_image_carousel/frontend/build/index.mjs
streamlit_image_carousel-1.0.4.dist-info/LICENSE
streamlit_image_carousel-1.0.4.dist-info/METADATA
streamlit_image_carousel-1.0.4.dist-info/WHEEL
streamlit_image_carousel-1.0.4.dist-info/top_level.txt
streamlit_image_carousel-1.0.4.dist-info/RECORD
