Metadata-Version: 2.1
Name: streamlit-image-carousel
Version: 1.0.4
Summary: Un composant Streamlit moderne pour créer des carrousels d'images interactifs
Author-email: Antoine <votre-email@example.com>
Project-URL: Homepage, https://github.com/2nzi/Streamlit-Composant
Project-URL: Issues, https://github.com/2nzi/Streamlit-Composant/issues
Project-URL: Source, https://github.com/2nzi/Streamlit-Composant
Keywords: streamlit,component,carousel,image,interactive,ui
Classifier: Development Status :: 4 - Beta
Classifier: Intended Audience :: Developers
Classifier: License :: OSI Approved :: MIT License
Classifier: Programming Language :: Python :: 3
Classifier: Programming Language :: Python :: 3.8
Classifier: Programming Language :: Python :: 3.9
Classifier: Programming Language :: Python :: 3.10
Classifier: Programming Language :: Python :: 3.11
Classifier: Topic :: Software Development :: Libraries :: Python Modules
Classifier: Topic :: Scientific/Engineering :: Visualization
Requires-Python: >=3.8
License-File: LICENSE
Requires-Dist: streamlit>=1.28.0
